gitools/__init__.py
gitools/__main__.py
gitools/gitools.py
gitools/module.py
gitools/modules/__init__.py
gitools/modules/restore_backup.py
gitools/modules/update_author.py
gitools/modules/update_date.py
gitools/modules/update_message.py
gitools/utils/__init__.py
gitools/utils/editor.py
gitools/utils/loading.py
gitools/utils/option_selector.py
gitools/utils/readkey.py
gitools/utils/utilities.py
Gitools-1.5.1.dist-info/LICENSE
Gitools-1.5.1.dist-info/METADATA
Gitools-1.5.1.dist-info/WHEEL
Gitools-1.5.1.dist-info/entry_points.txt
Gitools-1.5.1.dist-info/top_level.txt
Gitools-1.5.1.dist-info/RECORD
