Metadata-Version: 2.1
Name: Gitools
Version: 1.5.1
Summary: A handy tool to modify git history
Home-page: https://github.com/AliRezaBeigy/Gitools
Author: AliReza Beigy
Author-email: AliRezaBeigyKhu@gmail.com
License: MIT
Keywords: git history filter-branch change-date git-history
Platform: nt
Platform: posix
Classifier: Development Status :: 5 - Production/Stable
Classifier: Programming Language :: Python :: 3
Classifier: Programming Language :: Python :: 3.3
Classifier: Programming Language :: Python :: 3.4
Classifier: Programming Language :: Python :: 3.5
Classifier: Programming Language :: Python :: 3.6
Classifier: Intended Audience :: Developers
Classifier: Topic :: Software Development :: Version Control :: Git
Classifier: License :: OSI Approved :: MIT License
Requires-Python: >=3.6
